{"affiliation": {"affiliation-city": "Horsham", "affilname": "Arunside Primary School", "affiliation-country": "United Kingdom"}, "coredata": {"srctype": "p", "eid": "2-s2.0-85219195595", "prism:coverDate": "2025-01-07", "prism:aggregationType": "Conference Proceeding", "prism:url": "https://api.elsevier.com/content/abstract/scopus_id/85219195595", "subtypeDescription": "Conference Paper", "dc:creator": {"author": [{"ce:given-name": "Justin", "preferred-name": {"ce:given-name": "Justin", "ce:initials": "J.", "ce:surname": "Heath", "ce:indexed-name": "Heath J."}, "@seq": "1", "ce:initials": "J.", "@_fa": "true", "affiliation": {"@id": "132307968", "@href": "https://api.elsevier.com/content/affiliation/affiliation_id/132307968"}, "ce:surname": "Heath", "@auid": "59660952900", "author-url": "https://api.elsevier.com/content/author/author_id/59660952900", "ce:indexed-name": "Heath J."}]}, "link": [{"@_fa": "true", "@rel": "self", "@href": "https://api.elsevier.com/content/abstract/scopus_id/85219195595"}, {"@_fa": "true", "@rel": "scopus", "@href": "https://www.scopus.com/inward/record.uri?partnerID=HzOxMe3b&scp=85219195595&origin=inward"}, {"@_fa": "true", "@rel": "scopus-citedby", "@href": "https://www.scopus.com/inward/citedby.uri?partnerID=HzOxMe3b&scp=85219195595&origin=inward"}], "prism:isbn": "9798400711725", "prism:publicationName": "Proceedings - 9th Conference on Computing Education Practice, CEP 2025", "source-id": "21101278436", "citedby-count": "0", "subtype": "cp", "prism:pageRange": "25-28", "dc:title": "FLARE: A Framework Supporting Code Comprehension and Formative Assessment in Block-Based Programming Education", "prism:endingPage": "28", "openaccess": "0", "openaccessFlag": "false", "prism:doi": "10.1145/3702212.3702219", "prism:startingPage": "25", "dc:identifier": "SCOPUS_ID:85219195595", "dc:publisher": "Association for Computing Machinery, Inc"}}