{"affiliation": [{"affiliation-city": "Fairfield", "affilname": "Sacred Heart University Fairfield", "affiliation-country": "United States"}, {"affiliation-city": "Stockton", "affilname": "University of the Pacific, California", "affiliation-country": "United States"}, {"affiliation-city": "Charleston", "affilname": "College of Charleston", "affiliation-country": "United States"}, {"affiliation-city": "San Antonio", "affilname": "The University of Texas at San Antonio", "affiliation-country": "United States"}, {"affiliation-city": "Bucharest", "affilname": "University Politehnica of Bucharest", "affiliation-country": "Romania"}, {"affiliation-city": "Glasgow", "affilname": "University of Glasgow", "affiliation-country": "United Kingdom"}, {"affiliation-city": null, "affilname": "College of St.", "affiliation-country": "United States"}, {"affiliation-city": "Salt Lake City", "affilname": "Westminster College", "affiliation-country": "United States"}, {"affiliation-city": "Manhattan/New York", "affilname": "Borough of Manhattan Community College", "affiliation-country": "United States"}], "coredata": {"srctype": "p", "eid": "2-s2.0-85070896371", "prism:coverDate": "2019-07-02", "prism:aggregationType": "Conference Proceeding", "prism:url": "https://api.elsevier.com/content/abstract/scopus_id/85070896371", "subtypeDescription": "Conference Paper", "dc:creator": {"author": [{"ce:given-name": "Mohammad", "preferred-name": {"ce:given-name": "Mohammad", "ce:initials": "M.", "ce:surname": "Azhar", "ce:indexed-name": "Azhar M."}, "@seq": "1", "ce:initials": "M.", "@_fa": "true", "affiliation": {"@id": "101720136", "@href": "https://api.elsevier.com/content/affiliation/affiliation_id/101720136"}, "ce:surname": "Azhar", "@auid": "15055219300", "author-url": "https://api.elsevier.com/content/author/author_id/15055219300", "ce:indexed-name": "Azhar M."}]}, "link": [{"@_fa": "true", "@rel": "self", "@href": "https://api.elsevier.com/content/abstract/scopus_id/85070896371"}, {"@_fa": "true", "@rel": "scopus", "@href": "https://www.scopus.com/inward/record.uri?partnerID=HzOxMe3b&scp=85070896371&origin=inward"}, {"@_fa": "true", "@rel": "scopus-citedby", "@href": "https://www.scopus.com/inward/citedby.uri?partnerID=HzOxMe3b&scp=85070896371&origin=inward"}], "prism:isbn": "9781450363013", "prism:publicationName": "Annual Conference on Innovation and Technology in Computer Science Education, ITiCSE", "source-id": "21100197182", "citedby-count": "6", "subtype": "cp", "prism:pageRange": "251-252", "dc:title": "Securing the human: Broadening diversity in cybersecurity", "prism:endingPage": "252", "openaccess": "2", "openaccessFlag": null, "prism:doi": "10.1145/3304221.3325537", "prism:issn": "1942647X", "prism:startingPage": "251", "dc:identifier": "SCOPUS_ID:85070896371", "dc:publisher": "Association for Computing Machineryacmhelp@acm.org"}}