{"coredata": {"srctype": "p", "eid": "2-s2.0-85145836845", "prism:coverDate": "2023-01-06", "prism:aggregationType": "Conference Proceeding", "prism:url": "https://api.elsevier.com/content/abstract/scopus_id/85145836845", "subtypeDescription": "Conference Review", "link": [{"@_fa": "true", "@rel": "self", "@href": "https://api.elsevier.com/content/abstract/scopus_id/85145836845"}, {"@_fa": "true", "@rel": "scopus", "@href": "https://www.scopus.com/inward/record.uri?partnerID=HzOxMe3b&scp=85145836845&origin=inward"}, {"@_fa": "true", "@rel": "scopus-citedby", "@href": "https://www.scopus.com/inward/citedby.uri?partnerID=HzOxMe3b&scp=85145836845&origin=inward"}], "prism:isbn": "9781450398220", "prism:publicationName": "ACM International Conference Proceeding Series", "source-id": "11600154611", "citedby-count": "0", "subtype": "cr", "dc:title": "Proceedings of the 7th Conference on Computing Education Practice, CEP 2023", "openaccess": null, "openaccessFlag": null, "dc:identifier": "SCOPUS_ID:85145836845", "dc:publisher": "Association for Computing Machinery"}}